qiznlp/__init__.py
qiznlp/common/__init__.py
qiznlp/common/tfrecord_utils.py
qiznlp/common/train_helper.py
qiznlp/common/utils.py
qiznlp/common/modules/__init__.py
qiznlp/common/modules/beam_search.py
qiznlp/common/modules/bert_model.py
qiznlp/common/modules/birnn.py
qiznlp/common/modules/common_layers.py
qiznlp/common/modules/embedding.py
qiznlp/common/modules/encoder.py
qiznlp/common/modules/idcnn.py
qiznlp/common/modules/rerank.py
qiznlp/common/modules/DAM/__init__.py
qiznlp/common/modules/DAM/layers.py
qiznlp/common/modules/DAM/operations.py
qiznlp/common/modules/bert/__init__.py
qiznlp/common/modules/bert/modeling.py
qiznlp/common/modules/bert/optimization.py
qiznlp/common/modules/bert/tokenization.py
qiznlp/common/modules/bert/chinese_L-12_H-768_A-12/bert_config.json
qiznlp/common/modules/bert/chinese_L-12_H-768_A-12/vocab.txt
qiznlp/data/Douban_Sess662.txt
qiznlp/data/XHJ_5w.txt
qiznlp/data/dev.char.bmes.txt
qiznlp/data/mch_example_data.txt
qiznlp/data/test.char.bmes.txt
qiznlp/data/test.toutiao.cls.txt
qiznlp/data/train.char.bmes.txt
qiznlp/data/train.toutiao.cls.txt
qiznlp/data/valid.toutiao.cls.txt
qiznlp/deploy/__init__.py
qiznlp/deploy/example.py
qiznlp/deploy/web_API.py
qiznlp/model/__init__.py
qiznlp/model/cls_model.py
qiznlp/model/mch_model.py
qiznlp/model/multi_mch_model.py
qiznlp/model/multi_s2s_model.py
qiznlp/model/s2l_model.py
qiznlp/model/s2s_model.py
qiznlp/run/__init__.py
qiznlp/run/run_base.py
qiznlp/run/run_cls.py
qiznlp/run/run_mch.py
qiznlp/run/run_multi_mch.py
qiznlp/run/run_multi_s2s.py
qiznlp/run/run_s2l.py
qiznlp/run/run_s2s.py
QizNLP-0.1.4.dist-info/LICENSE
QizNLP-0.1.4.dist-info/METADATA
QizNLP-0.1.4.dist-info/WHEEL
QizNLP-0.1.4.dist-info/entry_points.txt
QizNLP-0.1.4.dist-info/top_level.txt
QizNLP-0.1.4.dist-info/RECORD
