Metadata-Version: 2.1
Name: QizNLP
Version: 0.1.4
Summary: Quick run NLP in many task
Home-page: https://github.com/Qznan/QizNLP
Author: Qznan
Author-email: summerzynqz@gmail.com
License: MPLv2.0
Keywords: NLP Classification Match Sequence_Label Senquence_to_Senquence Neural_Network
Platform: UNKNOWN
Classifier: Development Status :: 2 - Pre-Alpha
Classifier: Environment :: Console
Classifier: Environment :: MacOS X
Classifier: Intended Audience :: Developers
Classifier: License :: OSI Approved :: Mozilla Public License 2.0 (MPL 2.0)
Classifier: Programming Language :: Python :: 3
Classifier: Programming Language :: Python :: 3.6
Classifier: Programming Language :: Python :: 3.7
Classifier: Programming Language :: Python :: 3.8
Classifier: Topic :: Scientific/Engineering :: Artificial Intelligence
Requires-Python: >=3.6
Requires-Dist: jieba
Requires-Dist: tensorflow (<=1.14,>=1.8)
